teklib/__init__.py
teklib/info.py
teklib/administration/__init__.py
teklib/administration/tools.py
teklib/application/__init__.py
teklib/application/hos_nwt/__init__.py
teklib/application/hos_nwt/probes.py
teklib/application/wamit/__init__.py
teklib/application/wamit/wamit.py
teklib/metocean/__init__.py
teklib/metocean/current/__init__.py
teklib/metocean/wave/__init__.py
teklib/metocean/wave/crestdistributions.py
teklib/metocean/wave/heightdistributions.py
teklib/metocean/wave/spectrums.py
teklib/metocean/wind/__init__.py
teklib/miscellaneous/__init__.py
teklib/miscellaneous/io.py
teklib/miscellaneous/map.py
teklib/miscellaneous/math.py
teklib/reporting/__init__.py
teklib/reporting/latex.py
teklib/signal_analysis/__init__.py
teklib/signal_analysis/filter.py
teklib/signal_analysis/rainflow.py
teklib/signal_analysis/specpack.py
teklib/signal_analysis/stats.py
teklib/signal_analysis/timetools.py
teklib/software/__init__.py
teklib/software/common.py
teklib/software/mimosa.py
teklib/software/riflex_simo.py
teklib/software/wadam.py
teklib/software/wamit.py
teklib/structural/__init__.py
teklib/structural/inertia.py
teklib/wave_theory/__init__.py
teklib/wave_theory/irregular.py
teklib/wave_theory/mehaute.py
teklib/wave_theory/regular.py
teklib/wave_theory/spectrums.py
teklib/wave_theory/torsethaugen1996.py
teklib-1.0.11.dist-info/LICENSE
teklib-1.0.11.dist-info/METADATA
teklib-1.0.11.dist-info/WHEEL
teklib-1.0.11.dist-info/top_level.txt
teklib-1.0.11.dist-info/RECORD
